co_agent/__init__.py
co_agent/agents.py
co_agent/config.py
co_agent/database.py
co_agent/scraper.py
co_agent/tests/__init__.py
coagent_framework-0.2.1.dist-info/entry_points.txt
coagent_framework-0.2.1.dist-info/LICENSE
coagent_framework-0.2.1.dist-info/METADATA
coagent_framework-0.2.1.dist-info/WHEEL
coagent_framework-0.2.1.dist-info/RECORD
