Metadata-Version: 2.1
Name: coagent-framework
Version: 0.2.1
Summary: A Multi-Agent Library to create Linkedin posts from Blog Posts
Author: Dhruv Kumar
Author-email: 141584754+SnookyDru@users.noreply.github.com
Requires-Python: >=3.12.4,<4.0.0
Classifier: Programming Language :: Python :: 3
Requires-Dist: bs4 (>=0.0.2,<0.0.3)
Requires-Dist: langchain (>=0.3.7,<0.4.0)
Requires-Dist: langchain-google-genai (>=2.0.4,<3.0.0)
Requires-Dist: requests (>=2.32.3,<3.0.0)
